lcdp_logging_utils/__init__.py
lcdp_logging_utils/config.py
lcdp_logging_utils-1.5.9.dist-info/METADATA
lcdp_logging_utils-1.5.9.dist-info/WHEEL
lcdp_logging_utils-1.5.9.dist-info/RECORD
